alleycat_link/__init__.py
alleycat_link/extension.py
alleycat_link/link.py
alleycat_link/utils.py
alleycat_link-0.4.4.dist-info/LICENSE
alleycat_link-0.4.4.dist-info/METADATA
alleycat_link-0.4.4.dist-info/WHEEL
alleycat_link-0.4.4.dist-info/entry_points.txt
alleycat_link-0.4.4.dist-info/top_level.txt
alleycat_link-0.4.4.dist-info/RECORD
