Metadata-Version: 2.1
Name: alleycat-link
Version: 0.4.4
Summary: Plover plugin for communication with AlleyCAT
Author-email: Sammi de Guzman <sammi@sammdot.ca>
License: Copyright (c) 2022 Sammi de Guzman        
Project-URL: repository, https://github.com/sammdot/alleycat
Project-URL: homepage, https://alleycat.sammdot.ca
Project-URL: documentation, https://alleycat.readthedocs.io
Keywords: plover,plover_plugin
Classifier: Programming Language :: Python :: 3.7
Classifier: Programming Language :: Python :: 3.8
Classifier: Programming Language :: Python :: 3.9
Classifier: Programming Language :: Python :: 3.10
Requires-Python: >=3.7
License-File: LICENSE
Requires-Dist: plover (>=4.0.0.dev10)
